{
  "Yashasvi Jaiswal": {
    "batting": 17,
    "bowling": 0,
    "fielding": 0,
    "total": 17
  },
  "Vaibhav Sooryavanshi": {
    "batting": 125,
    "bowling": 0,
    "fielding": 0,
    "total": 125
  },
  "Dhruv Jurel": {
    "batting": 115,
    "bowling": 0,
    "fielding": 8,
    "total": 123
  },
  "Shimron Hetmyer": {
    "batting": -5,
    "bowling": 0,
    "fielding": 24,
    "total": 19
  },
  "Riyan Parag": {
    "batting": 3,
    "bowling": 0,
    "fielding": 0,
    "total": 3
  },
  "Ravindra Jadeja": {
    "batting": 20,
    "bowling": 37,
    "fielding": 0,
    "total": 57
  },
  "Ravi Bishnoi": {
    "batting": 0,
    "bowling": 55,
    "fielding": 0,
    "total": 55
  },
  "Jofra Archer": {
    "batting": 0,
    "bowling": 45,
    "fielding": 0,
    "total": 45
  },
  "Sandeep Sharma": {
    "batting": 0,
    "bowling": 20,
    "fielding": 0,
    "total": 20
  },
  "Phil Salt": {
    "batting": -5,
    "bowling": 0,
    "fielding": 0,
    "total": -5
  },
  "Virat Kohli": {
    "batting": 54,
    "bowling": 0,
    "fielding": 8,
    "total": 62
  },
  "Devdutt Padikkal": {
    "batting": 17,
    "bowling": 0,
    "fielding": 0,
    "total": 17
  },
  "Rajat Patidar": {
    "batting": 90,
    "bowling": 0,
    "fielding": 0,
    "total": 90
  },
  "Krunal Pandya": {
    "batting": 1,
    "bowling": 55,
    "fielding": 8,
    "total": 64
  },
  "Jitesh Sharma": {
    "batting": 5,
    "bowling": 0,
    "fielding": 8,
    "total": 13
  },
  "Tim David": {
    "batting": 15,
    "bowling": 0,
    "fielding": 0,
    "total": 15
  },
  "Romario Shepherd": {
    "batting": 41,
    "bowling": 0,
    "fielding": 0,
    "total": 41
  },
  "Bhuvneshwar Kumar": {
    "batting": 10,
    "bowling": 0,
    "fielding": 0,
    "total": 10
  },
  "Josh Hazlewood": {
    "batting": 0,
    "bowling": 45,
    "fielding": 8,
    "total": 53
  }
}